yadag/__init__.py
yadag-0.1.0.dist-info/METADATA
yadag-0.1.0.dist-info/WHEEL
yadag-0.1.0.dist-info/top_level.txt
yadag-0.1.0.dist-info/RECORD
