Metadata-Version: 2.4
Name: yadag
Version: 0.1.0
Summary: Do you like dags?
Author-email: "Argus J. Athanas" <argus@athanas.org>
License-Expression: Apache-2.0
Requires-Python: >=3.10
